odoo10_addon_product_stock_state-10.0.1.0.0.99.dev7-py3.8-nspkg.pth
odoo/addons/product_stock_state/README.rst
odoo/addons/product_stock_state/__init__.py
odoo/addons/product_stock_state/__manifest__.py
odoo/addons/product_stock_state/demo/product_category.xml
odoo/addons/product_stock_state/demo/product_product.xml
odoo/addons/product_stock_state/demo/res_groups.xml
odoo/addons/product_stock_state/i18n/fr.po
odoo/addons/product_stock_state/i18n/product_stock_state.pot
odoo/addons/product_stock_state/models/__init__.py
odoo/addons/product_stock_state/models/product_category.py
odoo/addons/product_stock_state/models/product_product.py
odoo/addons/product_stock_state/models/product_template.py
odoo/addons/product_stock_state/models/res_company.py
odoo/addons/product_stock_state/models/sale_config_settings.py
odoo/addons/product_stock_state/security/res_groups.xml
odoo/addons/product_stock_state/static/description/product_product_tree.png
odoo/addons/product_stock_state/tests/__init__.py
odoo/addons/product_stock_state/tests/test_product_stock_state.py
odoo/addons/product_stock_state/views/product_category_view.xml
odoo/addons/product_stock_state/views/product_product_view.xml
odoo/addons/product_stock_state/views/product_template_view.xml
odoo/addons/product_stock_state/views/sale_config_settings_view.xml
odoo10_addon_product_stock_state-10.0.1.0.0.99.dev7.dist-info/METADATA
odoo10_addon_product_stock_state-10.0.1.0.0.99.dev7.dist-info/WHEEL
odoo10_addon_product_stock_state-10.0.1.0.0.99.dev7.dist-info/namespace_packages.txt
odoo10_addon_product_stock_state-10.0.1.0.0.99.dev7.dist-info/top_level.txt
odoo10_addon_product_stock_state-10.0.1.0.0.99.dev7.dist-info/RECORD
