Metadata-Version: 2.1
Name: odoo10-addon-product-stock-state
Version: 10.0.1.0.0.99.dev7
Summary: Compute the state stock based onthe stock level and sale_ok field
Home-page: https://github.com/shopinvader/odoo-shopinvader
Author: Akretion,GRAP
License: AGPL-3
Platform: UNKNOWN
Classifier: Programming Language :: Python
Classifier: Framework :: Odoo
Classifier: License :: OSI Approved :: GNU Affero General Public License v3
Requires-Python: ~=2.7
Requires-Dist: odoo (<10.1dev,>=10.0)
